{
  "_class": "group",
  "booleanOperation": -1,
  "clippingMaskMode": 0,
  "do_objectID": "79ED66F1-325D-486F-8B30-4FB229338CEA",
  "exportOptions": {
    "_class": "exportOptions",
    "exportFormats": [
    ],
    "includedLayerIds": [
    ],
    "layerOptions": 0,
    "shouldTrim": false
  },
  "frame": {
    "_class": "rect",
    "constrainProportions": false,
    "do_objectID": "63A0B152-9C13-487F-AC16-8FED964FF4B7",
    "height": 15,
    "width": 95,
    "x": 189.5,
    "y": 104.25
  },
  "groupLayout": {
    "_class": "MSImmutableFreeformGroupLayout",
    "do_objectID": "753B9819-E49C-497F-9A8E-025165E1C79E"
  },
  "hasClickThrough": false,
  "hasClippingMask": false,
  "isFixedToViewport": false,
  "isFlippedHorizontal": false,
  "isFlippedVertical": false,
  "isLocked": false,
  "isVisible": true,
  "layerListExpandedType": 0,
  "layers": [
    {
      "class": "star",
      "id": "157ACB90-8A57-4730-B99E-2E088DFA3B1F"
    },
    {
      "class": "star",
      "id": "DBCF5DD6-AC00-451C-80EB-8484402343C5"
    },
    {
      "class": "star",
      "id": "3A78CBE0-0DAE-4F26-B49C-B659018BF165"
    },
    {
      "class": "star",
      "id": "4183E474-BDBA-42B4-80EF-B71BA7291CF5"
    },
    {
      "class": "star",
      "id": "25614535-609C-4DB2-B6DF-695C21008DDB"
    }
  ],
  "name": "Group 13",
  "nameIsFixed": false,
  "resizingConstraint": 63,
  "resizingType": 0,
  "rotation": 0,
  "shouldBreakMaskChain": false,
  "style": {
    "_class": "style",
    "do_objectID": "6B3C3DFB-92EB-4474-86BC-A1948D52A1A5",
    "endMarkerType": 0,
    "miterLimit": 10,
    "startMarkerType": 0,
    "windingRule": 1
  }
}