{
  "_class": "group",
  "booleanOperation": -1,
  "clippingMaskMode": 0,
  "do_objectID": "2366B109-D070-4DC6-8851-76A92D0E8D53",
  "exportOptions": {
    "_class": "exportOptions",
    "exportFormats": [
    ],
    "includedLayerIds": [
    ],
    "layerOptions": 0,
    "shouldTrim": false
  },
  "frame": {
    "_class": "rect",
    "constrainProportions": false,
    "do_objectID": "507D87BD-E8B4-4C93-AE68-BFC06FA4F542",
    "height": 401,
    "width": 401,
    "x": 519,
    "y": 116
  },
  "groupLayout": {
    "_class": "MSImmutableFreeformGroupLayout",
    "do_objectID": "6542E84D-E8D4-44CF-8928-60FC335C4214"
  },
  "hasClickThrough": false,
  "hasClippingMask": false,
  "isFixedToViewport": false,
  "isFlippedHorizontal": false,
  "isFlippedVertical": false,
  "isLocked": false,
  "isVisible": true,
  "layerListExpandedType": 0,
  "layers": [
    {
      "class": "rectangle",
      "id": "954BBC8E-9E57-41A8-A878-121BD030523B"
    },
    {
      "class": "group",
      "id": "E0689AB8-98E2-40CF-A11B-526777099271"
    },
    {
      "class": "group",
      "id": "87146612-4C55-4AAA-8007-652FB1E6BC36"
    }
  ],
  "name": "Group 16",
  "nameIsFixed": false,
  "resizingConstraint": 63,
  "resizingType": 0,
  "rotation": 0,
  "shouldBreakMaskChain": false,
  "style": {
    "_class": "style",
    "do_objectID": "EFD54171-415B-4107-990D-1FBC0236EE8E",
    "endMarkerType": 0,
    "miterLimit": 10,
    "startMarkerType": 0,
    "windingRule": 1
  }
}