{
  "_class": "group",
  "booleanOperation": -1,
  "clippingMaskMode": 0,
  "do_objectID": "581176B9-CFCF-41A9-A01C-D38AEE3BA428",
  "exportOptions": {
    "_class": "exportOptions",
    "exportFormats": [
    ],
    "includedLayerIds": [
    ],
    "layerOptions": 0,
    "shouldTrim": false
  },
  "frame": {
    "_class": "rect",
    "constrainProportions": false,
    "height": 307,
    "width": 184,
    "x": 392,
    "y": 73
  },
  "groupLayout": {
    "_class": "MSImmutableFreeformGroupLayout"
  },
  "hasClickThrough": false,
  "hasClippingMask": false,
  "isFixedToViewport": false,
  "isFlippedHorizontal": false,
  "isFlippedVertical": false,
  "isLocked": false,
  "isVisible": true,
  "layerListExpandedType": 0,
  "layers": [
    {
      "class": "group",
      "id": "D34C27ED-59B4-476F-B55D-AA71B57D1B43"
    },
    {
      "class": "group",
      "id": "726B8819-AAEC-4698-B9C4-1BB344B74A57"
    },
    {
      "class": "text",
      "id": "BC733F3B-EE46-4574-842D-162A7D9DC254"
    },
    {
      "class": "text",
      "id": "C99A9EF2-A2DE-4A23-B01F-434D0829AE1C"
    }
  ],
  "name": "Group 2",
  "nameIsFixed": false,
  "resizingConstraint": 63,
  "resizingType": 0,
  "rotation": 0,
  "shouldBreakMaskChain": false,
  "style": {
    "_class": "style",
    "endMarkerType": 0,
    "miterLimit": 10,
    "startMarkerType": 0,
    "windingRule": 1
  }
}