{
  "_class": "group",
  "booleanOperation": -1,
  "clippingMaskMode": 0,
  "do_objectID": "741E51D6-F1DD-4656-BB84-06AE30EBE6AC",
  "exportOptions": {
    "_class": "exportOptions",
    "exportFormats": [
    ],
    "includedLayerIds": [
    ],
    "layerOptions": 0,
    "shouldTrim": false
  },
  "frame": {
    "_class": "rect",
    "constrainProportions": false,
    "do_objectID": "C76A23E0-73A0-4297-A8ED-78198027146F",
    "height": 8,
    "width": 12,
    "x": 0,
    "y": 5
  },
  "groupLayout": {
    "_class": "MSImmutableFreeformGroupLayout",
    "do_objectID": "7FBABD8A-E49F-473D-9796-88FAD39E3BA8"
  },
  "hasClickThrough": false,
  "hasClippingMask": false,
  "isFixedToViewport": false,
  "isFlippedHorizontal": false,
  "isFlippedVertical": false,
  "isLocked": false,
  "isVisible": true,
  "layerListExpandedType": 0,
  "layers": [
    {
      "class": "shapePath",
      "id": "23212F49-BE29-4CB9-9521-A742E6D1D11D"
    },
    {
      "class": "shapePath",
      "id": "6CC5C15E-B112-4F61-BD77-5DCD3857920A"
    }
  ],
  "name": "Group 5",
  "nameIsFixed": false,
  "resizingConstraint": 63,
  "resizingType": 0,
  "rotation": 0,
  "shouldBreakMaskChain": false,
  "style": {
    "_class": "style",
    "blur": {
      "_class": "blur",
      "center": "{0.5, 0.5}",
      "do_objectID": "FDDD3D41-C1B5-451A-8404-10AF91E54FCF",
      "isEnabled": false,
      "motionAngle": 0,
      "radius": 7.5,
      "saturation": 1,
      "type": 0
    },
    "do_objectID": "62D92009-FD25-489B-AD49-C290A1556B46",
    "endMarkerType": 0,
    "miterLimit": 10,
    "startMarkerType": 0,
    "windingRule": 1
  }
}