{
  "_class": "group",
  "booleanOperation": -1,
  "clippingMaskMode": 0,
  "do_objectID": "3945E246-F1FF-4D54-8938-97F60DE1230E",
  "exportOptions": {
    "_class": "exportOptions",
    "exportFormats": [
    ],
    "includedLayerIds": [
    ],
    "layerOptions": 0,
    "shouldTrim": false
  },
  "frame": {
    "_class": "rect",
    "constrainProportions": false,
    "do_objectID": "8C3AAB59-7622-4288-A767-292E33B7B309",
    "height": 15,
    "width": 95,
    "x": 245.5,
    "y": 40.75
  },
  "groupLayout": {
    "_class": "MSImmutableFreeformGroupLayout",
    "do_objectID": "6B19256D-9FAA-4847-B276-F789B487CA7E"
  },
  "hasClickThrough": false,
  "hasClippingMask": false,
  "isFixedToViewport": false,
  "isFlippedHorizontal": false,
  "isFlippedVertical": false,
  "isLocked": false,
  "isVisible": true,
  "layerListExpandedType": 0,
  "layers": [
    {
      "class": "star",
      "id": "3C868F5F-B421-429C-AEB5-E602FF97134E"
    },
    {
      "class": "star",
      "id": "8E39842B-18BA-4BE3-9E67-7E4981701F9D"
    },
    {
      "class": "star",
      "id": "7BE3204C-75E1-4B36-876B-8F30BFF92996"
    },
    {
      "class": "star",
      "id": "DEC62BC8-0724-42BA-AFF7-726502A7EEF3"
    },
    {
      "class": "star",
      "id": "C50E413B-373E-41B7-889C-95D806C9D232"
    }
  ],
  "name": "Group 13",
  "nameIsFixed": false,
  "resizingConstraint": 63,
  "resizingType": 0,
  "rotation": 0,
  "shouldBreakMaskChain": false,
  "style": {
    "_class": "style",
    "do_objectID": "894DB300-AC46-41B3-916D-698AB5BE8C4C",
    "endMarkerType": 0,
    "miterLimit": 10,
    "startMarkerType": 0,
    "windingRule": 1
  }
}