{
  "_class": "group",
  "booleanOperation": -1,
  "clippingMaskMode": 0,
  "do_objectID": "CED85763-51D5-4320-80CA-0868E9E3A78A",
  "exportOptions": {
    "_class": "exportOptions",
    "exportFormats": [
    ],
    "includedLayerIds": [
    ],
    "layerOptions": 0,
    "shouldTrim": false
  },
  "frame": {
    "_class": "rect",
    "constrainProportions": false,
    "do_objectID": "7CC9B004-0074-497C-9109-B9757E1CDC29",
    "height": 50,
    "width": 345,
    "x": 30,
    "y": 127
  },
  "groupLayout": {
    "_class": "MSImmutableFreeformGroupLayout",
    "do_objectID": "B53853B8-FE87-4096-94CB-ACA5D0B90BC8"
  },
  "hasClickThrough": false,
  "hasClippingMask": false,
  "isFixedToViewport": false,
  "isFlippedHorizontal": false,
  "isFlippedVertical": false,
  "isLocked": false,
  "isVisible": true,
  "layerListExpandedType": 0,
  "layers": [
    {
      "class": "rectangle",
      "id": "E26B4EDB-0163-44B0-9D0C-9CD046C33237"
    },
    {
      "class": "group",
      "id": "A661E3E4-92AB-4226-95E9-51AB36061C57"
    },
    {
      "class": "group",
      "id": "F79693C4-3D58-446B-90BC-21FA15B99295"
    }
  ],
  "name": "Group 10",
  "nameIsFixed": false,
  "resizingConstraint": 63,
  "resizingType": 0,
  "rotation": 0,
  "shouldBreakMaskChain": false,
  "style": {
    "_class": "style",
    "do_objectID": "D0946467-CEC1-4256-A3EE-961BCE5E8C82",
    "endMarkerType": 0,
    "miterLimit": 10,
    "startMarkerType": 0,
    "windingRule": 1
  }
}