{
  "_class": "group",
  "booleanOperation": -1,
  "clippingMaskMode": 0,
  "do_objectID": "6CF48E85-33F0-4022-95C2-7C9C9AA2A8E0",
  "exportOptions": {
    "_class": "exportOptions",
    "exportFormats": [
    ],
    "includedLayerIds": [
    ],
    "layerOptions": 0,
    "shouldTrim": false
  },
  "frame": {
    "_class": "rect",
    "constrainProportions": false,
    "do_objectID": "CAB270B7-2249-451D-AA4A-6E9EF759868E",
    "height": 31,
    "width": 185,
    "x": 36.75,
    "y": 4.5
  },
  "groupLayout": {
    "_class": "MSImmutableFreeformGroupLayout",
    "do_objectID": "A0C660AE-539B-45DA-98DB-66DB2D425A41"
  },
  "hasClickThrough": false,
  "hasClippingMask": false,
  "isFixedToViewport": false,
  "isFlippedHorizontal": false,
  "isFlippedVertical": false,
  "isLocked": false,
  "isVisible": true,
  "layerListExpandedType": 0,
  "layers": [
    {
      "class": "text",
      "id": "AF769559-6417-499F-AAE7-8921FCD8C0A6"
    },
    {
      "class": "shapeGroup",
      "id": "CC10FB35-5BF3-4A01-BA08-230E0E1BF306"
    }
  ],
  "name": "Group",
  "nameIsFixed": false,
  "resizingConstraint": 63,
  "resizingType": 0,
  "rotation": 0,
  "shouldBreakMaskChain": false,
  "style": {
    "_class": "style",
    "blur": {
      "_class": "blur",
      "center": "{0.5, 0.5}",
      "do_objectID": "7B836240-EDA9-4E43-A137-FED9C91B38C4",
      "isEnabled": false,
      "motionAngle": 0,
      "radius": 7.5,
      "saturation": 1,
      "type": 0
    },
    "do_objectID": "F7E6317D-E1BB-4A3C-ADF5-6597C19AEB6B",
    "endMarkerType": 0,
    "miterLimit": 10,
    "startMarkerType": 0,
    "windingRule": 1
  }
}