{
  "_class": "group",
  "booleanOperation": -1,
  "clippingMaskMode": 0,
  "do_objectID": "641719D4-A241-448B-8667-35A23BCEFDE0",
  "exportOptions": {
    "_class": "exportOptions",
    "exportFormats": [
    ],
    "includedLayerIds": [
    ],
    "layerOptions": 0,
    "shouldTrim": false
  },
  "frame": {
    "_class": "rect",
    "constrainProportions": false,
    "do_objectID": "1F247F30-3C4E-4910-A021-5DD8F1728909",
    "height": 178,
    "width": 694,
    "x": 307,
    "y": 562
  },
  "groupLayout": {
    "_class": "MSImmutableFreeformGroupLayout",
    "do_objectID": "B74BC223-6604-41D7-81FB-8F06A2412F35"
  },
  "hasClickThrough": false,
  "hasClippingMask": false,
  "isFixedToViewport": false,
  "isFlippedHorizontal": false,
  "isFlippedVertical": false,
  "isLocked": false,
  "isVisible": true,
  "layerListExpandedType": 0,
  "layers": [
    {
      "class": "rectangle",
      "id": "DFD9DE44-3DF0-41FB-9FB3-21056A11CB98"
    },
    {
      "class": "group",
      "id": "45832290-6F59-42A3-B7AD-DEB5586F8890"
    },
    {
      "class": "text",
      "id": "FD91BAAF-A992-4003-B5C8-E85A1A22A5D8"
    }
  ],
  "name": "Group 5",
  "nameIsFixed": false,
  "resizingConstraint": 63,
  "resizingType": 0,
  "rotation": 0,
  "shouldBreakMaskChain": false,
  "style": {
    "_class": "style",
    "do_objectID": "6F18974D-82DA-455E-ACE2-2890DE4AEEE9",
    "endMarkerType": 0,
    "miterLimit": 10,
    "startMarkerType": 0,
    "windingRule": 1
  }
}