{
  "_class": "artboard",
  "backgroundColor": {
    "_class": "color",
    "alpha": 1,
    "blue": 1,
    "green": 1,
    "red": 1
  },
  "booleanOperation": -1,
  "clippingMaskMode": 0,
  "do_objectID": "36C8E632-093C-4C20-A5A6-0C2A0FE2EDAA",
  "exportOptions": {
    "_class": "exportOptions",
    "exportFormats": [
    ],
    "includedLayerIds": [
    ],
    "layerOptions": 0,
    "shouldTrim": false
  },
  "frame": {
    "_class": "rect",
    "constrainProportions": false,
    "height": 1236,
    "width": 1440,
    "x": -597,
    "y": -457
  },
  "groupLayout": {
    "_class": "MSImmutableFreeformGroupLayout"
  },
  "hasBackgroundColor": false,
  "hasClickThrough": true,
  "hasClippingMask": false,
  "horizontalRulerData": {
    "_class": "rulerData",
    "base": 0,
    "guides": [
    ]
  },
  "includeBackgroundColorInExport": true,
  "includeInCloudUpload": true,
  "isFixedToViewport": false,
  "isFlippedHorizontal": false,
  "isFlippedVertical": false,
  "isFlowHome": false,
  "isLocked": false,
  "isVisible": true,
  "layerListExpandedType": 0,
  "layers": [
    {
      "class": "rectangle",
      "id": "E253BECF-7861-45B3-ABF2-89394D389B94"
    },
    {
      "class": "rectangle",
      "id": "773FA108-112E-4627-8EBF-D88853F5678E"
    },
    {
      "class": "text",
      "id": "610D33B9-92A3-42C5-898E-45C6EAC3CD3D"
    },
    {
      "class": "rectangle",
      "id": "46CA6C3E-D630-4524-993D-B12AA3AD0E59"
    },
    {
      "class": "rectangle",
      "id": "4FCD55A0-D446-4501-BFDB-AF2E0ED19161"
    },
    {
      "class": "rectangle",
      "id": "75E14EB0-91CE-4700-A8AD-B6A064A2B8FE"
    },
    {
      "class": "text",
      "id": "0D8DD13D-F961-484A-8C64-D619E7FE5280"
    },
    {
      "class": "rectangle",
      "id": "8346C45F-8DCA-4601-9FA2-1C70BE576212"
    },
    {
      "class": "rectangle",
      "id": "7C7EF584-A366-4E34-971F-A1AC2AE5CDEB"
    },
    {
      "class": "text",
      "id": "3DAF65C9-0DF1-4529-9F43-78C433314395"
    },
    {
      "class": "text",
      "id": "02E436D5-1AAD-4342-9479-06FB36E1457E"
    },
    {
      "class": "rectangle",
      "id": "92DAD5BC-DA34-4AD8-A95E-09AD94046D7A"
    },
    {
      "class": "text",
      "id": "E72DE525-60A7-4B02-BBB3-68912B42BDF1"
    },
    {
      "class": "rectangle",
      "id": "2396C75C-B6CF-4193-B9C2-1F7723A6649E"
    },
    {
      "class": "rectangle",
      "id": "A228270E-9EA4-47CC-934E-0025A55EA71B"
    },
    {
      "class": "text",
      "id": "8BBD1F25-7806-440F-AAB9-96B6EDBEFAE6"
    },
    {
      "class": "text",
      "id": "87EDD8FB-5746-4854-A4BA-01D779BEFA68"
    },
    {
      "class": "rectangle",
      "id": "D2EE93D6-7699-4695-9BA6-29D39B8DDC28"
    },
    {
      "class": "text",
      "id": "6B6F4804-3F92-493A-B153-2B6F001D1495"
    },
    {
      "class": "symbolInstance",
      "id": "90BF0AEE-8E90-438C-9BEF-97946C61D1A5"
    }
  ],
  "layout": {
    "_class": "layoutGrid",
    "columnWidth": 40.16666666666666,
    "drawHorizontal": false,
    "drawHorizontalLines": false,
    "drawVertical": true,
    "gutterHeight": 12,
    "gutterWidth": 12,
    "guttersOutside": false,
    "horizontalOffset": 100,
    "isEnabled": true,
    "numberOfColumns": 24,
    "rowHeightMultiplication": 5,
    "totalWidth": 1240
  },
  "name": "Alerts",
  "nameIsFixed": false,
  "presetDictionary": {
    "allowResizedMatching": 0,
    "height": 1024,
    "name": "Desktop HD",
    "offersLandscapeVariant": 0,
    "width": 1440
  },
  "resizesContent": false,
  "resizingConstraint": 63,
  "resizingType": 0,
  "rotation": 0,
  "shouldBreakMaskChain": true,
  "style": {
    "_class": "style",
    "endMarkerType": 0,
    "miterLimit": 10,
    "startMarkerType": 0,
    "windingRule": 1
  },
  "verticalRulerData": {
    "_class": "rulerData",
    "base": 0,
    "guides": [
    ]
  }
}