{
  "_class": "shapeGroup",
  "booleanOperation": -1,
  "clippingMaskMode": 0,
  "do_objectID": "17B7D20A-B169-4C1D-9F50-3B3CCB09EBCE",
  "exportOptions": {
    "_class": "exportOptions",
    "exportFormats": [
    ],
    "includedLayerIds": [
    ],
    "layerOptions": 0,
    "shouldTrim": false
  },
  "frame": {
    "_class": "rect",
    "constrainProportions": false,
    "do_objectID": "F63E6FD1-F4F8-4C48-A0C5-C21F66B74253",
    "height": 26.16640073394776,
    "width": 26.16640073394776,
    "x": 0,
    "y": 6
  },
  "groupLayout": {
    "_class": "MSImmutableFreeformGroupLayout",
    "do_objectID": "F8191096-B166-4541-AB2C-077D93993B6A"
  },
  "hasClickThrough": false,
  "hasClippingMask": false,
  "isFixedToViewport": false,
  "isFlippedHorizontal": false,
  "isFlippedVertical": false,
  "isLocked": false,
  "isVisible": true,
  "layerListExpandedType": 0,
  "layers": [
    {
      "class": "shapePath",
      "id": "B436C410-1EEA-48D1-B1B3-72E466133270"
    },
    {
      "class": "shapePath",
      "id": "939C9250-76BB-47A6-8B5C-0CD93CE3336F"
    },
    {
      "class": "shapePath",
      "id": "4EA23291-3F80-492F-A2EF-9F8280889F9F"
    }
  ],
  "name": "Shape",
  "nameIsFixed": false,
  "resizingConstraint": 63,
  "resizingType": 0,
  "rotation": 0,
  "shouldBreakMaskChain": false,
  "style": {
    "_class": "style",
    "blur": {
      "_class": "blur",
      "center": "{0.5, 0.5}",
      "do_objectID": "88970ED3-4EA0-41A1-9A4C-84E0FEA2C2BF",
      "isEnabled": false,
      "motionAngle": 0,
      "radius": 7.741383462974238,
      "saturation": 1,
      "type": 0
    },
    "borders": [
      {
        "_class": "border",
        "color": {
          "_class": "color",
          "alpha": 1,
          "blue": 0.3411764705882353,
          "green": 0.3411764705882353,
          "red": 0.3411764705882353
        },
        "fillType": 0,
        "isEnabled": true,
        "position": 0,
        "thickness": 1
      }
    ],
    "do_objectID": "4B89C15D-EAE5-405B-AAB4-8E67B063D709",
    "endMarkerType": 0,
    "fills": [
      {
        "_class": "fill",
        "color": {
          "_class": "color",
          "alpha": 1,
          "blue": 0.3411764705882353,
          "green": 0.3411764705882353,
          "red": 0.3411764705882353
        },
        "fillType": 0,
        "isEnabled": true,
        "noiseIndex": 0,
        "noiseIntensity": 0,
        "patternFillType": 1,
        "patternTileScale": 1
      }
    ],
    "miterLimit": 10,
    "startMarkerType": 0,
    "windingRule": 0
  },
  "windingRule": 0
}