{
  "_class": "group",
  "booleanOperation": -1,
  "clippingMaskMode": 0,
  "do_objectID": "A826EDCC-E3FA-48BE-A1EC-9BD573780735",
  "exportOptions": {
    "_class": "exportOptions",
    "exportFormats": [
    ],
    "includedLayerIds": [
    ],
    "layerOptions": 0,
    "shouldTrim": false
  },
  "frame": {
    "_class": "rect",
    "constrainProportions": false,
    "do_objectID": "13DD9F2C-12AC-4EB1-B6A6-2EF1464B1127",
    "height": 35,
    "width": 346,
    "x": 30,
    "y": 350
  },
  "groupLayout": {
    "_class": "MSImmutableFreeformGroupLayout",
    "do_objectID": "A34B0261-82B2-4589-B805-122273BA602D"
  },
  "hasClickThrough": false,
  "hasClippingMask": false,
  "isFixedToViewport": false,
  "isFlippedHorizontal": false,
  "isFlippedVertical": false,
  "isLocked": false,
  "isVisible": true,
  "layerListExpandedType": 0,
  "layers": [
    {
      "class": "text",
      "id": "22968091-5591-4465-A06B-8B2A3D03B310"
    },
    {
      "class": "symbolInstance",
      "id": "6EEE1934-4FD3-4451-B91E-1D4420330C36"
    }
  ],
  "name": "Group 20",
  "nameIsFixed": false,
  "resizingConstraint": 63,
  "resizingType": 0,
  "rotation": 0,
  "shouldBreakMaskChain": false,
  "style": {
    "_class": "style",
    "do_objectID": "551909E7-6CC0-44EC-AB7B-AFEB4EE2DDF6",
    "endMarkerType": 0,
    "miterLimit": 10,
    "startMarkerType": 0,
    "windingRule": 1
  }
}